aibox/data_lake/__init__.py
aibox/data_lake/client.py
aibox/data_lake/config.py
aibox/data_lake/factory.py
aibox/data_lake/gcp.py
aibox/data_lake/cli/__init__.py
aibox/data_lake/cli/bucket.py
aibox/data_lake/cli/config.py
aibox/data_lake/cli/dataset.py
aibox/data_lake/cli/main.py
aibox/data_lake/cli/utils.py
aibox/data_lake/core/__init__.py
aibox/data_lake/core/bucket.py
aibox/data_lake/core/dataset.py
aibox/data_lake/core/tabular_dataset.py
aibox_data_lake-1.2.0.dist-info/licenses/LICENSE
aibox_data_lake-1.2.0.dist-info/METADATA
aibox_data_lake-1.2.0.dist-info/WHEEL
aibox_data_lake-1.2.0.dist-info/entry_points.txt
aibox_data_lake-1.2.0.dist-info/top_level.txt
aibox_data_lake-1.2.0.dist-info/RECORD
