Metadata-Version: 2.4
Name: aibox-data-lake
Version: 1.2.0
Summary: AiBox Data Lake Toolkit.
Author: AiBox Lab
Maintainer-email: Moésio Filho <moesio.f@gmail.com>
Project-URL: Homepage, https://aiboxlab.org/data-lake
Project-URL: Documentation, https://aiboxlab.org/data-lake
Project-URL: Repository, https://github.com/aiboxlab/data-lake
Project-URL: Issues, https://github.com/aiboxlab/data-lake/issues
Project-URL: Changelog, https://github.com/aiboxlab/data-lake/blob/main/CHANGELOG.md
Classifier: Programming Language :: Python :: 3.12
Classifier: Programming Language :: Python :: 3.13
Classifier: Development Status :: 3 - Alpha
Requires-Python: >=3.12
License-File: LICENSE
Requires-Dist: google-cloud-storage<4,>=3.3.1
Requires-Dist: ibis-framework[duckdb]<12,>=11.0.0
Requires-Dist: pandas<3,>=2.3.2
Requires-Dist: platformdirs<5,>=4.4.0
Requires-Dist: pyarrow<22,>=21.0.0
Requires-Dist: pydantic<3,>=2.11.7
Requires-Dist: pydantic-settings<3,>=2.10.1
Requires-Dist: rich<15,>=14.1.0
Requires-Dist: smart-open[all]<8,>=7.3.1
Requires-Dist: tqdm>=4.67.2
Requires-Dist: typer<1,>=0.17.4
Requires-Dist: uv<1,>=0.8.15
Dynamic: license-file
